[["Descent into cave","Cave start","","","","","","","",""],{"XPos":53.51813,"YPos":181.54,"ZPos":694.273,"QRotX":-2.4196148E-05,"QRotY":0.70443296,"QRotZ":-1.8678538E-05,"QRotW":0.7097705,"XSpd":0,"YSpd":0,"ZSpd":0},{"XPos":232.92795,"YPos":129.3955,"ZPos":694.2016,"QRotX":0.069699176,"QRotY":0.7036633,"QRotZ":-0.06965628,"QRotW":0.7036675,"XSpd":0,"YSpd":0,"ZSpd":0},{"XPos":0,"YPos":0,"ZPos":0,"QRotX":0,"QRotY":0,"QRotZ":0,"QRotW":0,"XSpd":0,"YSpd":0,"ZSpd":0},{"XPos":0,"YPos":0,"ZPos":0,"QRotX":0,"QRotY":0,"QRotZ":0,"QRotW":0,"XSpd":0,"YSpd":0,"ZSpd":0},{"XPos":0,"YPos":0,"ZPos":0,"QRotX":0,"QRotY":0,"QRotZ":0,"QRotW":0,"XSpd":0,"YSpd":0,"ZSpd":0},{"XPos":0,"YPos":0,"ZPos":0,"QRotX":0,"QRotY":0,"QRotZ":0,"QRotW":0,"XSpd":0,"YSpd":0,"ZSpd":0},{"XPos":0,"YPos":0,"ZPos":0,"QRotX":0,"QRotY":0,"QRotZ":0,"QRotW":0,"XSpd":0,"YSpd":0,"ZSpd":0},{"XPos":0,"YPos":0,"ZPos":0,"QRotX":0,"QRotY":0,"QRotZ":0,"QRotW":0,"XSpd":0,"YSpd":0,"ZSpd":0},{"XPos":0,"YPos":0,"ZPos":0,"QRotX":0,"QRotY":0,"QRotZ":0,"QRotW":0,"XSpd":0,"YSpd":0,"ZSpd":0},{"XPos":0,"YPos":0,"ZPos":0,"QRotX":0,"QRotY":0,"QRotZ":0,"QRotW":0,"XSpd":0,"YSpd":0,"ZSpd":0}]